mdp_playground/__init__.py
mdp_playground/analysis/__init__.py
mdp_playground/analysis/analysis.py
mdp_playground/analysis/radar_chart.py
mdp_playground/config_processor/__init__.py
mdp_playground/config_processor/config_processor.py
mdp_playground/envs/__init__.py
mdp_playground/envs/gym_env_wrapper.py
mdp_playground/envs/mujoco_env_wrapper.py
mdp_playground/envs/rl_toy_env.py
mdp_playground/scripts/__init__.py
mdp_playground/scripts/run_experiments.py
mdp_playground/spaces/__init__.py
mdp_playground/spaces/box_extended.py
mdp_playground/spaces/discrete_extended.py
mdp_playground/spaces/grid_action_space.py
mdp_playground/spaces/image_continuous.py
mdp_playground/spaces/image_multi_discrete.py
mdp_playground/spaces/multi_discrete_extended.py
mdp_playground/spaces/test_image_continuous.py
mdp_playground/spaces/test_image_multi_discrete.py
mdp_playground/spaces/tuple_extended.py
mdp_playground-0.0.2.dist-info/entry_points.txt
mdp_playground-0.0.2.dist-info/LICENSE
mdp_playground-0.0.2.dist-info/WHEEL
mdp_playground-0.0.2.dist-info/METADATA
mdp_playground-0.0.2.dist-info/RECORD
