Metadata-Version: 2.1
Name: mdp-playground
Version: 0.0.2
Summary: A python package to design and debug RL agents
Home-page: https://automl.github.io/mdp-playground
License: Apache-2.0
Author: Raghu Rajan
Author-email: rajanr@cs.uni-freiburg.de
Requires-Python: >=3.6,<4.0
Classifier: Intended Audience :: Developers
Classifier: Intended Audience :: Education
Classifier: Intended Audience :: Science/Research
Classifier: License :: OSI Approved :: Apache Software License
Classifier: Natural Language :: English
Classifier: Operating System :: OS Independent
Classifier: Programming Language :: Python :: 3
Classifier: Programming Language :: Python :: 3.6
Classifier: Programming Language :: Python :: 3.7
Classifier: Programming Language :: Python :: 3.8
Classifier: Programming Language :: Python :: 3.9
Classifier: Topic :: Scientific/Engineering :: Artificial Intelligence
Provides-Extra: extras
Provides-Extra: extras_cont
Provides-Extra: extras_disc
Provides-Extra: extras_test
Requires-Dist: atari-py (==0.2.5)
Requires-Dist: colorama (>=0.4.4,<0.5.0)
Requires-Dist: configspace (==0.4.10); extra == "extras" or extra == "extras_disc" or extra == "extras_cont" or extra == "extras_test"
Requires-Dist: dill (>=0.3.3,<0.4.0)
Requires-Dist: gym[atari] (==0.14.0)
Requires-Dist: matplotlib (>=3.3.4,<4.0.0)
Requires-Dist: mujoco-py (==2.0.2.13); extra == "extras_cont"
Requires-Dist: numpy (>=1.19.5,<2.0.0)
Requires-Dist: pandas (==0.25.0); extra == "extras" or extra == "extras_disc" or extra == "extras_cont" or extra == "extras_test"
Requires-Dist: pillow (>=6.1.0,<7.0.0); extra == "extras" or extra == "extras_disc"
Requires-Dist: ray[rllib,debug,default] (>=1.3.0,<2.0.0); extra == "extras"
Requires-Dist: requests (==2.22.0); extra == "extras" or extra == "extras_disc" or extra == "extras_cont" or extra == "extras_test"
Requires-Dist: scipy (>=1.3.0,<2.0.0); extra == "extras" or extra == "extras_disc" or extra == "extras_cont" or extra == "extras_test"
Requires-Dist: tensorflow (==2.2.0); extra == "extras"
Requires-Dist: tensorflow-probability (==0.9.0); extra == "extras_cont" or extra == "extras_test"
Project-URL: Bug Tracker, https://github.com/automl/mdp-playground/issues
Project-URL: Repository, https://github.com/automl/mdp-playground
